{"_id":{"$oid":"675d54eaf4dec4fdb979a210"},"date":{"$date":"2024-03-20T00:00:00Z"},"dailyStats":{"totalRevenue":{"amount":4500000,"currency":"₮"},"dailyRevenue":{"amount":650000,"currency":"₮"},"unpaidAmount":{"amount":180000,"currency":"₮"},"refundAmount":{"amount":25000,"currency":"₮"}},"transactions":[{"patientId":{"$oid":"675d54eaf4dec4fdb979a211"},"patientName":"Б.Болд","registerNumber":"УБ99112233","serviceType":"Үзлэг","amount":{"value":45000,"currency":"₮"},"status":"Төлөгдсөн","paymentMethod":"Бэлэн","createdAt":{"$date":"2024-03-20T01:00:00Z"}},{"patientId":{"$oid":"675d54eaf4dec4fdb979a212"},"patientName":"Д.Сүхбат","registerNumber":"УБ88112233","serviceType":"Шинжилгээ","amount":{"value":120000,"currency":"₮"},"status":"Төлөгдөөгүй","dueDate":{"$date":"2024-03-27T00:00:00Z"},"createdAt":{"$date":"2024-03-20T02:30:00Z"}}]}
